era5_to_int/WPSUtils.py
era5_to_int/__init__.py
era5_to_int/ecmwf_coeffs
era5_to_int/era5_to_int.py
era5_to_int/fortran_io.py
era5_to_int-0.2.0.dist-info/METADATA
era5_to_int-0.2.0.dist-info/WHEEL
era5_to_int-0.2.0.dist-info/entry_points.txt
era5_to_int-0.2.0.dist-info/licenses/LICENSE
era5_to_int-0.2.0.dist-info/RECORD
