Metadata-Version: 2.4
Name: era5_to_int
Version: 0.2.0
Summary: A simple utility for converting ERA5 netCDF files to the WPS intermediate format
Project-URL: Documentation, https://github.com/envlib/era5_to_int
Project-URL: Issues, https://github.com/envlib/era5_to_int/issues
Project-URL: Source, https://github.com/envlib/era5_to_int
Author-email: Mike Kittridge <mullenkamp1@gmail.com>
License-Expression: Apache-2.0
License-File: LICENSE
Keywords: ERA5,WPS,WRF
Classifier: Development Status :: 4 - Beta
Classifier: Programming Language :: Python
Classifier: Programming Language :: Python :: 3.11
Classifier: Programming Language :: Python :: Implementation :: CPython
Classifier: Programming Language :: Python :: Implementation :: PyPy
Requires-Python: >=3.11
Requires-Dist: netcdf4
Requires-Dist: numpy>=2
Requires-Dist: typer==0.19.2
